secmail/__init__.py
secmail/client.py
secmail/objects.py
secmail-1.0.2.dist-info/LICENSE
secmail-1.0.2.dist-info/METADATA
secmail-1.0.2.dist-info/WHEEL
secmail-1.0.2.dist-info/top_level.txt
secmail-1.0.2.dist-info/RECORD
