Metadata-Version: 2.1
Name: secmail
Version: 1.0.2
Summary: A Libarry to generate emails!
Home-page: https://github.com/SirLez/secmail
Author: SirLez
Author-email: SirLezDV@gmail.com
License: MIT
Download-URL: https://github.com/SirLez/secmail/archive/refs/heads/main.zip
Keywords: SirLez,sirlez,api,python,python3,python3.x,official,secmail,1secmail,mail,email-generator-python,email-generator,email-python
Platform: UNKNOWN
Requires-Dist: requests
